MLVRAtests/__init__.py
MLVRAtests/ecological_inference.py
MLVRAtests/kmean_district.py
MLVRAtests-0.1.0.dist-info/LICENSE.txt
MLVRAtests-0.1.0.dist-info/METADATA
MLVRAtests-0.1.0.dist-info/WHEEL
MLVRAtests-0.1.0.dist-info/top_level.txt
MLVRAtests-0.1.0.dist-info/RECORD
