Metadata-Version: 2.1
Name: MLVRAtests
Version: 0.1.0
Summary: Set of tools to measure and test for violations of the 1982 Voting Rights Amendment
Home-page: 
Author: Robert Edwardes
Author-email: robie@fairlines.org
License: UNKNOWN
Platform: UNKNOWN
Classifier: Development Status :: 4 - Beta
Classifier: License :: OSI Approved :: MIT License
Classifier: Programming Language :: Python :: 3
Classifier: Programming Language :: Python :: 3.6
Classifier: Programming Language :: Python :: 3.7
Classifier: Programming Language :: Python :: 3.8
Classifier: Programming Language :: Python :: 3.9
Classifier: Programming Language :: Python :: 3.10
Classifier: Programming Language :: Python :: 3 :: Only
Requires-Python: >=3.6, <4
License-File: LICENSE.txt
Requires-Dist: pandas
Requires-Dist: pymc3
Requires-Dist: seaborn
Requires-Dist: matplotlib
Requires-Dist: sklearn
Requires-Dist: shapely
Requires-Dist: geopandas
Requires-Dist: numpy
